redditminer/__init__.py
redditminer/__main__.py
redditminer/downloader.py
redditminer/scraper.py
redditminer-1.0.2.dist-info/METADATA
redditminer-1.0.2.dist-info/WHEEL
redditminer-1.0.2.dist-info/top_level.txt
redditminer-1.0.2.dist-info/RECORD
