Metadata-Version: 2.4
Name: RedditMiner
Version: 1.0.2
Summary: A Python tool for scraping images, galleries, and comments from Reddit using browser cookies.
Home-page: https://github.com/MisbahKhan0009/RedditMiner
Author: Misbah Khan
Author-email: Misbah Khan <misbahkhan007@gmail.com>
Keywords: reddit,scraper,images,gallery,comments,download
Classifier: Programming Language :: Python :: 3
Classifier: License :: OSI Approved :: MIT License
Classifier: Operating System :: OS Independent
Classifier: Intended Audience :: End Users/Desktop
Classifier: Topic :: Internet :: WWW/HTTP
Classifier: Topic :: Utilities
Requires-Python: >=3.7
Requires-Dist: requests>=2.0.0
Dynamic: author
Dynamic: home-page
Dynamic: requires-python
